dash_dynamic_grid/DynamicGrid.py
dash_dynamic_grid/__init__.py
dash_dynamic_grid/_imports_.py
dash_dynamic_grid/column_formatter.py
dash_dynamic_grid/dash_dynamic_grid.min.js
dash_dynamic_grid/dash_dynamic_grid.min.js.map
dash_dynamic_grid/metadata.json
dash_dynamic_grid/package-info.json
dash_dynamic_grid-0.0.6.dist-info/LICENSE
dash_dynamic_grid-0.0.6.dist-info/METADATA
dash_dynamic_grid-0.0.6.dist-info/WHEEL
dash_dynamic_grid-0.0.6.dist-info/top_level.txt
dash_dynamic_grid-0.0.6.dist-info/RECORD
