Metadata-Version: 2.1
Name: dash-dynamic-grid
Version: 0.0.6
Summary: High performance grid for dash applications
Home-page: UNKNOWN
Author: Tomasz Rewak <tomasz.rewak@gmail.com>
Author-email: UNKNOWN
License: MIT
Platform: UNKNOWN
Classifier: Framework :: Dash
